novaclient/__init__.py
novaclient/api_versions.py
novaclient/base.py
novaclient/client.py
novaclient/crypto.py
novaclient/exceptions.py
novaclient/extension.py
novaclient/i18n.py
novaclient/shell.py
novaclient/utils.py
novaclient/tests/__init__.py
novaclient/tests/functional/README.rst
novaclient/tests/functional/__init__.py
novaclient/tests/functional/base.py
novaclient/tests/functional/clouds.yaml.sample
novaclient/tests/functional/test_auth.py
novaclient/tests/functional/api/__init__.py
novaclient/tests/functional/api/test_servers.py
novaclient/tests/functional/hooks/check_resources.py
novaclient/tests/functional/v2/__init__.py
novaclient/tests/functional/v2/fake_crypto.py
novaclient/tests/functional/v2/test_aggregates.py
novaclient/tests/functional/v2/test_consoles.py
novaclient/tests/functional/v2/test_device_tagging.py
novaclient/tests/functional/v2/test_extended_attributes.py
novaclient/tests/functional/v2/test_flavor.py
novaclient/tests/functional/v2/test_flavor_access.py
novaclient/tests/functional/v2/test_hypervisors.py
novaclient/tests/functional/v2/test_image_meta.py
novaclient/tests/functional/v2/test_instance_action.py
novaclient/tests/functional/v2/test_instance_usage_audit_log.py
novaclient/tests/functional/v2/test_instances.py
novaclient/tests/functional/v2/test_keypairs.py
novaclient/tests/functional/v2/test_migrations.py
novaclient/tests/functional/v2/test_networks.py
novaclient/tests/functional/v2/test_os_services.py
novaclient/tests/functional/v2/test_quota_classes.py
novaclient/tests/functional/v2/test_quotas.py
novaclient/tests/functional/v2/test_resize.py
novaclient/tests/functional/v2/test_server_groups.py
novaclient/tests/functional/v2/test_servers.py
novaclient/tests/functional/v2/test_trigger_crash_dump.py
novaclient/tests/functional/v2/test_usage.py
novaclient/tests/functional/v2/legacy/__init__.py
novaclient/tests/functional/v2/legacy/test_consoles.py
novaclient/tests/functional/v2/legacy/test_extended_attributes.py
python_novaclient-18.11.0.dist-info/AUTHORS
python_novaclient-18.11.0.dist-info/LICENSE
python_novaclient-18.11.0.dist-info/METADATA
python_novaclient-18.11.0.dist-info/WHEEL
python_novaclient-18.11.0.dist-info/entry_points.txt
python_novaclient-18.11.0.dist-info/pbr.json
python_novaclient-18.11.0.dist-info/top_level.txt
python_novaclient-18.11.0.dist-info/RECORD
