Metadata-Version: 2.1
Name: python-novaclient
Version: 18.11.0
Summary: Client library for OpenStack Compute API
Home-page: https://docs.openstack.org/python-novaclient/latest
Author: OpenStack
Author-email: openstack-discuss@lists.openstack.org
License: Apache License, Version 2.0
Classifier: Development Status :: 5 - Production/Stable
Classifier: Environment :: Console
Classifier: Environment :: OpenStack
Classifier: Intended Audience :: Developers
Classifier: Intended Audience :: Information Technology
Classifier: License :: OSI Approved :: Apache Software License
Classifier: Operating System :: OS Independent
Classifier: Programming Language :: Python
Classifier: Programming Language :: Python :: 3
Classifier: Programming Language :: Python :: 3.9
Classifier: Programming Language :: Python :: 3.10
Classifier: Programming Language :: Python :: 3.11
Classifier: Programming Language :: Python :: 3.12
Classifier: Programming Language :: Python :: 3 :: Only
Classifier: Programming Language :: Python :: Implementation :: CPython
Requires-Python: >=3.9
License-File: LICENSE
Requires-Dist: pbr>=3.0.0
Requires-Dist: keystoneauth1>=3.5.0
Requires-Dist: iso8601>=0.1.11
Requires-Dist: oslo.i18n>=3.15.3
Requires-Dist: oslo.serialization>=2.20.0
Requires-Dist: oslo.utils>=3.33.0
Requires-Dist: PrettyTable>=0.7.2
Requires-Dist: stevedore>=2.0.1
